stderrstdoutcapture/README.MD
stderrstdoutcapture/__init__.py
stderrstdoutcapture/requirements.txt
stderrstdoutcapture/thirdparty.json
stderrstdoutcapture-0.10.dist-info/LICENSE.rst
stderrstdoutcapture-0.10.dist-info/METADATA
stderrstdoutcapture-0.10.dist-info/WHEEL
stderrstdoutcapture-0.10.dist-info/top_level.txt
stderrstdoutcapture-0.10.dist-info/RECORD
