Metadata-Version: 2.1
Name: stderrstdoutcapture
Version: 0.10
Summary: captures temporarily stdout and stderr
Home-page: https://github.com/hansalemaos/stderrstdoutcapture
Author: Johannes Fischer
Author-email: aulasparticularesdealemaosp@gmail.com
License: MIT
Keywords: capture,stdout,stderr
Classifier: Development Status :: 4 - Beta
Classifier: Programming Language :: Python :: 3 :: Only
Classifier: Programming Language :: Python :: 3.10
Classifier: Topic :: Software Development :: Libraries :: Python Modules
Classifier: Topic :: Utilities
License-File: LICENSE.rst
